{
    "nome": "Boehmerwald Dias Letivos",
    "codigo": "606/A",
    "detalhe": null,
    "servicos": {
        "62": [
            {
                "sentido": "Ida",
                "horarios": [
                    {
                        "hora": "07:00",
                        "obs": [
                            {
                                "tipo": "ADAPTADO",
                                "valor": "Veículo com elevador"
                            }
                        ]
                    },
                    {
                        "hora": "12:40",
                        "obs": [
                            {
                                "tipo": "ADAPTADO",
                                "valor": "Veículo com elevador"
                            }
                        ]
                    }
                ]
            }
        ]
    },
    "tipo": "convencional",
    "slug": "606-boehmerwald-dias-letivos"
}