{
    "nome": "Centenário",
    "codigo": "820",
    "detalhe": null,
    "servicos": {
        "62": [
            {
                "sentido": "Saída Centenário (Apae",
                "horarios": [
                    {
                        "hora": "04:45",
                        "obs": []
                    },
                    {
                        "hora": "04:45",
                        "obs": []
                    },
                    {
                        "hora": "05:05",
                        "obs": []
                    },
                    {
                        "hora": "06:55",
                        "obs": []
                    },
                    {
                        "hora": "07:15",
                        "obs": []
                    },
                    {
                        "hora": "07:30",
                        "obs": []
                    },
                    {
                        "hora": "09:40",
                        "obs": []
                    },
                    {
                        "hora": "11:40",
                        "obs": []
                    },
                    {
                        "hora": "12:20",
                        "obs": []
                    },
                    {
                        "hora": "13:05",
                        "obs": []
                    },
                    {
                        "hora": "14:05",
                        "obs": []
                    },
                    {
                        "hora": "14:28",
                        "obs": []
                    },
                    {
                        "hora": "15:40",
                        "obs": []
                    },
                    {
                        "hora": "16:40",
                        "obs": []
                    },
                    {
                        "hora": "17:00",
                        "obs": []
                    },
                    {
                        "hora": "17:35",
                        "obs": []
                    },
                    {
                        "hora": "23:10",
                        "obs": []
                    },
                    {
                        "hora": "23:34",
                        "obs": []
                    }
                ]
            },
            {
                "sentido": "Saída Terminal Urbano",
                "horarios": [
                    {
                        "hora": "04:25",
                        "obs": []
                    },
                    {
                        "hora": "06:35",
                        "obs": []
                    },
                    {
                        "hora": "06:50",
                        "obs": []
                    },
                    {
                        "hora": "07:05",
                        "obs": []
                    },
                    {
                        "hora": "09:20",
                        "obs": []
                    },
                    {
                        "hora": "11:20",
                        "obs": []
                    },
                    {
                        "hora": "12:00",
                        "obs": []
                    },
                    {
                        "hora": "12:50",
                        "obs": []
                    },
                    {
                        "hora": "15:20",
                        "obs": []
                    },
                    {
                        "hora": "16:20",
                        "obs": []
                    },
                    {
                        "hora": "16:40",
                        "obs": []
                    },
                    {
                        "hora": "17:15",
                        "obs": []
                    }
                ]
            }
        ]
    },
    "tipo": "convencional",
    "slug": "820-centenario"
}