{
    "nome": "Rua Nova Trento",
    "codigo": null,
    "detalhe": null,
    "servicos": {
        "62": [
            {
                "sentido": "Saída Do Terminal",
                "horarios": [
                    {
                        "hora": "07:05",
                        "obs": []
                    }
                ]
            },
            {
                "sentido": "Saída Da Rua Nova Trento",
                "horarios": [
                    {
                        "hora": "07:15",
                        "obs": []
                    },
                    {
                        "hora": "15:40",
                        "obs": []
                    },
                    {
                        "hora": "18:30",
                        "obs": []
                    }
                ]
            }
        ],
        "1": [
            {
                "sentido": "Saída Do Terminal",
                "horarios": [
                    {
                        "hora": "07:05",
                        "obs": []
                    }
                ]
            },
            {
                "sentido": "Saída Da Rua Nova Trento",
                "horarios": [
                    {
                        "hora": "07:15",
                        "obs": []
                    }
                ]
            }
        ]
    },
    "tipo": "convencional",
    "slug": "r-nova-trento"
}