{
    "nome": "Atalanta",
    "codigo": "0-40",
    "detalhe": null,
    "servicos": {
        "62": [
            {
                "sentido": "Ida",
                "horarios": [
                    {
                        "hora": "17:30",
                        "obs": []
                    }
                ]
            },
            {
                "sentido": "Volta",
                "horarios": [
                    {
                        "hora": "05:50",
                        "obs": []
                    }
                ]
            }
        ]
    },
    "tipo": "convencional",
    "slug": "0-40-atalanta"
}