{
    "nome": "Alto Bela Aliança (Alto Matador",
    "codigo": "2BB",
    "detalhe": null,
    "servicos": {
        "62": [
            {
                "sentido": "Saída Do Terminal Urbano",
                "horarios": [
                    {
                        "hora": "06:10",
                        "obs": []
                    },
                    {
                        "hora": "12:05",
                        "obs": []
                    },
                    {
                        "hora": "15:00",
                        "obs": []
                    },
                    {
                        "hora": "16:55",
                        "obs": []
                    },
                    {
                        "hora": "18:05",
                        "obs": []
                    },
                    {
                        "hora": "22:10",
                        "obs": []
                    }
                ]
            },
            {
                "sentido": "Saída Do Alto Matador",
                "horarios": [
                    {
                        "hora": "06:40",
                        "obs": []
                    },
                    {
                        "hora": "12:40",
                        "obs": []
                    },
                    {
                        "hora": "15:30",
                        "obs": []
                    },
                    {
                        "hora": "17:30",
                        "obs": []
                    }
                ]
            }
        ],
        "1": [
            {
                "sentido": "Saída Do Terminal Urbano",
                "horarios": [
                    {
                        "hora": "06:15",
                        "obs": []
                    },
                    {
                        "hora": "12:10",
                        "obs": []
                    }
                ]
            },
            {
                "sentido": "Saída Do Alto Matador",
                "horarios": [
                    {
                        "hora": "06:45",
                        "obs": []
                    },
                    {
                        "hora": "12:45",
                        "obs": []
                    }
                ]
            }
        ]
    },
    "tipo": "convencional",
    "slug": "2bb-alto-bela-alianca-alto-mat"
}