{
    "nome": "Cordeiros / Fazenda",
    "codigo": "T1A",
    "detalhe": null,
    "servicos": {
        "62": [
            {
                "sentido": "Ida",
                "horarios": [
                    {
                        "hora": "05:40",
                        "obs": []
                    },
                    {
                        "hora": "06:00",
                        "obs": []
                    },
                    {
                        "hora": "06:15",
                        "obs": []
                    },
                    {
                        "hora": "06:30",
                        "obs": []
                    },
                    {
                        "hora": "06:45",
                        "obs": []
                    },
                    {
                        "hora": "07:00",
                        "obs": []
                    },
                    {
                        "hora": "07:15",
                        "obs": []
                    },
                    {
                        "hora": "07:40",
                        "obs": []
                    },
                    {
                        "hora": "08:00",
                        "obs": []
                    },
                    {
                        "hora": "08:15",
                        "obs": []
                    },
                    {
                        "hora": "08:40",
                        "obs": []
                    },
                    {
                        "hora": "08:55",
                        "obs": []
                    },
                    {
                        "hora": "09:40",
                        "obs": []
                    },
                    {
                        "hora": "10:00",
                        "obs": []
                    },
                    {
                        "hora": "10:35",
                        "obs": []
                    },
                    {
                        "hora": "11:00",
                        "obs": []
                    },
                    {
                        "hora": "11:35",
                        "obs": []
                    },
                    {
                        "hora": "12:00",
                        "obs": []
                    },
                    {
                        "hora": "12:35",
                        "obs": []
                    },
                    {
                        "hora": "12:50",
                        "obs": []
                    },
                    {
                        "hora": "13:00",
                        "obs": []
                    },
                    {
                        "hora": "13:15",
                        "obs": []
                    },
                    {
                        "hora": "13:40",
                        "obs": []
                    },
                    {
                        "hora": "14:00",
                        "obs": []
                    },
                    {
                        "hora": "14:35",
                        "obs": []
                    },
                    {
                        "hora": "15:00",
                        "obs": []
                    },
                    {
                        "hora": "15:35",
                        "obs": []
                    },
                    {
                        "hora": "16:05",
                        "obs": []
                    },
                    {
                        "hora": "16:30",
                        "obs": []
                    },
                    {
                        "hora": "16:45",
                        "obs": []
                    },
                    {
                        "hora": "17:00",
                        "obs": []
                    },
                    {
                        "hora": "17:30",
                        "obs": []
                    },
                    {
                        "hora": "18:00",
                        "obs": []
                    },
                    {
                        "hora": "18:15",
                        "obs": []
                    },
                    {
                        "hora": "18:35",
                        "obs": []
                    },
                    {
                        "hora": "19:00",
                        "obs": []
                    },
                    {
                        "hora": "19:15",
                        "obs": []
                    },
                    {
                        "hora": "19:25",
                        "obs": []
                    },
                    {
                        "hora": "20:45",
                        "obs": []
                    },
                    {
                        "hora": "21:30",
                        "obs": []
                    },
                    {
                        "hora": "22:10",
                        "obs": []
                    },
                    {
                        "hora": "22:35",
                        "obs": []
                    },
                    {
                        "hora": "23:10",
                        "obs": []
                    }
                ]
            },
            {
                "sentido": "Volta",
                "horarios": [
                    {
                        "hora": "06:00",
                        "obs": []
                    },
                    {
                        "hora": "06:20",
                        "obs": []
                    },
                    {
                        "hora": "06:40",
                        "obs": []
                    },
                    {
                        "hora": "06:50",
                        "obs": []
                    },
                    {
                        "hora": "07:15",
                        "obs": []
                    },
                    {
                        "hora": "07:30",
                        "obs": []
                    },
                    {
                        "hora": "07:45",
                        "obs": []
                    },
                    {
                        "hora": "08:15",
                        "obs": []
                    },
                    {
                        "hora": "08:35",
                        "obs": []
                    },
                    {
                        "hora": "08:45",
                        "obs": []
                    },
                    {
                        "hora": "09:15",
                        "obs": []
                    },
                    {
                        "hora": "09:20",
                        "obs": []
                    },
                    {
                        "hora": "10:10",
                        "obs": []
                    },
                    {
                        "hora": "10:35",
                        "obs": []
                    },
                    {
                        "hora": "11:05",
                        "obs": []
                    },
                    {
                        "hora": "11:30",
                        "obs": []
                    },
                    {
                        "hora": "12:00",
                        "obs": []
                    },
                    {
                        "hora": "12:25",
                        "obs": []
                    },
                    {
                        "hora": "13:10",
                        "obs": []
                    },
                    {
                        "hora": "13:20",
                        "obs": []
                    },
                    {
                        "hora": "13:30",
                        "obs": []
                    },
                    {
                        "hora": "13:45",
                        "obs": []
                    },
                    {
                        "hora": "14:10",
                        "obs": []
                    },
                    {
                        "hora": "14:30",
                        "obs": []
                    },
                    {
                        "hora": "15:05",
                        "obs": []
                    },
                    {
                        "hora": "15:30",
                        "obs": []
                    },
                    {
                        "hora": "16:00",
                        "obs": []
                    },
                    {
                        "hora": "16:35",
                        "obs": []
                    },
                    {
                        "hora": "16:55",
                        "obs": []
                    },
                    {
                        "hora": "17:15",
                        "obs": []
                    },
                    {
                        "hora": "17:30",
                        "obs": []
                    },
                    {
                        "hora": "17:50",
                        "obs": []
                    },
                    {
                        "hora": "18:10",
                        "obs": []
                    },
                    {
                        "hora": "18:35",
                        "obs": []
                    },
                    {
                        "hora": "18:55",
                        "obs": []
                    },
                    {
                        "hora": "19:15",
                        "obs": []
                    },
                    {
                        "hora": "19:35",
                        "obs": []
                    },
                    {
                        "hora": "19:50",
                        "obs": []
                    },
                    {
                        "hora": "20:05",
                        "obs": []
                    },
                    {
                        "hora": "21:10",
                        "obs": []
                    },
                    {
                        "hora": "21:50",
                        "obs": []
                    }
                ]
            }
        ],
        "1": [
            {
                "sentido": "Ida",
                "horarios": [
                    {
                        "hora": "05:40",
                        "obs": []
                    },
                    {
                        "hora": "06:00",
                        "obs": []
                    },
                    {
                        "hora": "06:15",
                        "obs": []
                    },
                    {
                        "hora": "06:30",
                        "obs": []
                    },
                    {
                        "hora": "06:45",
                        "obs": []
                    },
                    {
                        "hora": "07:00",
                        "obs": []
                    },
                    {
                        "hora": "07:15",
                        "obs": []
                    },
                    {
                        "hora": "07:40",
                        "obs": []
                    },
                    {
                        "hora": "08:00",
                        "obs": []
                    },
                    {
                        "hora": "08:15",
                        "obs": []
                    },
                    {
                        "hora": "08:40",
                        "obs": []
                    },
                    {
                        "hora": "08:55",
                        "obs": []
                    },
                    {
                        "hora": "09:40",
                        "obs": []
                    },
                    {
                        "hora": "10:00",
                        "obs": []
                    },
                    {
                        "hora": "10:35",
                        "obs": []
                    },
                    {
                        "hora": "11:00",
                        "obs": []
                    },
                    {
                        "hora": "11:30",
                        "obs": []
                    },
                    {
                        "hora": "12:05",
                        "obs": []
                    },
                    {
                        "hora": "12:35",
                        "obs": []
                    },
                    {
                        "hora": "12:50",
                        "obs": []
                    },
                    {
                        "hora": "13:00",
                        "obs": []
                    },
                    {
                        "hora": "13:15",
                        "obs": []
                    },
                    {
                        "hora": "13:35",
                        "obs": []
                    },
                    {
                        "hora": "14:00",
                        "obs": []
                    },
                    {
                        "hora": "14:29",
                        "obs": []
                    },
                    {
                        "hora": "15:45",
                        "obs": []
                    },
                    {
                        "hora": "16:50",
                        "obs": []
                    },
                    {
                        "hora": "18:27",
                        "obs": []
                    },
                    {
                        "hora": "20:05",
                        "obs": []
                    },
                    {
                        "hora": "22:05",
                        "obs": []
                    }
                ]
            },
            {
                "sentido": "Volta",
                "horarios": [
                    {
                        "hora": "06:00",
                        "obs": []
                    },
                    {
                        "hora": "06:20",
                        "obs": []
                    },
                    {
                        "hora": "06:40",
                        "obs": []
                    },
                    {
                        "hora": "06:50",
                        "obs": []
                    },
                    {
                        "hora": "07:15",
                        "obs": []
                    },
                    {
                        "hora": "07:30",
                        "obs": []
                    },
                    {
                        "hora": "07:45",
                        "obs": []
                    },
                    {
                        "hora": "08:15",
                        "obs": []
                    },
                    {
                        "hora": "08:30",
                        "obs": []
                    },
                    {
                        "hora": "08:45",
                        "obs": []
                    },
                    {
                        "hora": "09:15",
                        "obs": []
                    },
                    {
                        "hora": "09:25",
                        "obs": []
                    },
                    {
                        "hora": "10:05",
                        "obs": []
                    },
                    {
                        "hora": "10:30",
                        "obs": []
                    },
                    {
                        "hora": "11:00",
                        "obs": []
                    },
                    {
                        "hora": "11:20",
                        "obs": []
                    },
                    {
                        "hora": "12:05",
                        "obs": []
                    },
                    {
                        "hora": "12:30",
                        "obs": []
                    },
                    {
                        "hora": "13:05",
                        "obs": []
                    },
                    {
                        "hora": "13:20",
                        "obs": []
                    },
                    {
                        "hora": "13:30",
                        "obs": []
                    },
                    {
                        "hora": "13:45",
                        "obs": []
                    },
                    {
                        "hora": "14:00",
                        "obs": []
                    },
                    {
                        "hora": "14:18",
                        "obs": []
                    },
                    {
                        "hora": "15:35",
                        "obs": []
                    },
                    {
                        "hora": "17:11",
                        "obs": []
                    },
                    {
                        "hora": "19:01",
                        "obs": []
                    },
                    {
                        "hora": "20:45",
                        "obs": []
                    }
                ]
            }
        ]
    },
    "tipo": "convencional",
    "slug": "t1a-cordeiros-faz"
}