{
    "nome": "Executivo Costa Do Moçambique",
    "codigo": "1128",
    "detalhe": null,
    "servicos": {
        "62": [
            {
                "sentido": "Saída Costa Do Moçambique",
                "horarios": [
                    {
                        "hora": "05:55",
                        "obs": [
                            {
                                "tipo": "MEIA_VIAGEM",
                                "valor": "Meia viagem"
                            }
                        ]
                    },
                    {
                        "hora": "06:10",
                        "obs": [
                            {
                                "tipo": "MEIA_VIAGEM",
                                "valor": "Meia viagem"
                            }
                        ]
                    },
                    {
                        "hora": "06:35",
                        "obs": [
                            {
                                "tipo": "MEIA_VIAGEM",
                                "valor": "Meia viagem"
                            }
                        ]
                    },
                    {
                        "hora": "06:55",
                        "obs": [
                            {
                                "tipo": "MEIA_VIAGEM",
                                "valor": "Meia viagem"
                            }
                        ]
                    },
                    {
                        "hora": "07:50",
                        "obs": [
                            {
                                "tipo": "MEIA_VIAGEM",
                                "valor": "Meia viagem"
                            }
                        ]
                    },
                    {
                        "hora": "09:15",
                        "obs": [
                            {
                                "tipo": "PREVISTO",
                                "valor": "Horário previsto"
                            }
                        ]
                    },
                    {
                        "hora": "09:47",
                        "obs": [
                            {
                                "tipo": "PREVISTO",
                                "valor": "Horário previsto"
                            }
                        ]
                    },
                    {
                        "hora": "11:38",
                        "obs": [
                            {
                                "tipo": "PREVISTO",
                                "valor": "Horário previsto"
                            }
                        ]
                    },
                    {
                        "hora": "12:28",
                        "obs": [
                            {
                                "tipo": "PREVISTO",
                                "valor": "Horário previsto"
                            }
                        ]
                    },
                    {
                        "hora": "13:32",
                        "obs": [
                            {
                                "tipo": "PREVISTO",
                                "valor": "Horário previsto"
                            }
                        ]
                    },
                    {
                        "hora": "14:29",
                        "obs": [
                            {
                                "tipo": "PREVISTO",
                                "valor": "Horário previsto"
                            }
                        ]
                    },
                    {
                        "hora": "15:39",
                        "obs": [
                            {
                                "tipo": "PREVISTO",
                                "valor": "Horário previsto"
                            }
                        ]
                    },
                    {
                        "hora": "16:56",
                        "obs": [
                            {
                                "tipo": "PREVISTO",
                                "valor": "Horário previsto"
                            }
                        ]
                    }
                ]
            },
            {
                "sentido": "Saída Tecif - Plataforma 3 - Box 4",
                "horarios": [
                    {
                        "hora": "08:08",
                        "obs": []
                    },
                    {
                        "hora": "08:40",
                        "obs": []
                    },
                    {
                        "hora": "10:30",
                        "obs": []
                    },
                    {
                        "hora": "11:15",
                        "obs": []
                    },
                    {
                        "hora": "12:18",
                        "obs": []
                    },
                    {
                        "hora": "13:05",
                        "obs": []
                    },
                    {
                        "hora": "14:15",
                        "obs": []
                    },
                    {
                        "hora": "15:32",
                        "obs": []
                    },
                    {
                        "hora": "17:05",
                        "obs": []
                    },
                    {
                        "hora": "17:30",
                        "obs": []
                    },
                    {
                        "hora": "18:00",
                        "obs": []
                    },
                    {
                        "hora": "18:42",
                        "obs": []
                    },
                    {
                        "hora": "19:15",
                        "obs": []
                    }
                ]
            }
        ],
        "1": [
            {
                "sentido": "Saída Costa Do Moçambique",
                "horarios": [
                    {
                        "hora": "06:35",
                        "obs": [
                            {
                                "tipo": "MEIA_VIAGEM",
                                "valor": "Meia viagem"
                            }
                        ]
                    },
                    {
                        "hora": "07:20",
                        "obs": [
                            {
                                "tipo": "MEIA_VIAGEM",
                                "valor": "Meia viagem"
                            }
                        ]
                    },
                    {
                        "hora": "08:00",
                        "obs": [
                            {
                                "tipo": "MEIA_VIAGEM",
                                "valor": "Meia viagem"
                            }
                        ]
                    },
                    {
                        "hora": "08:47",
                        "obs": [
                            {
                                "tipo": "PREVISTO",
                                "valor": "Horário previsto"
                            }
                        ]
                    },
                    {
                        "hora": "10:40",
                        "obs": [
                            {
                                "tipo": "PREVISTO",
                                "valor": "Horário previsto"
                            }
                        ]
                    },
                    {
                        "hora": "11:30",
                        "obs": [
                            {
                                "tipo": "PREVISTO",
                                "valor": "Horário previsto"
                            }
                        ]
                    }
                ]
            },
            {
                "sentido": "Saída Tecif - Plataforma 3 - Box 4",
                "horarios": [
                    {
                        "hora": "07:50",
                        "obs": []
                    },
                    {
                        "hora": "09:35",
                        "obs": []
                    },
                    {
                        "hora": "10:25",
                        "obs": []
                    },
                    {
                        "hora": "11:35",
                        "obs": []
                    },
                    {
                        "hora": "12:20",
                        "obs": []
                    },
                    {
                        "hora": "13:15",
                        "obs": []
                    }
                ]
            }
        ]
    },
    "tipo": "executivo",
    "slug": "1128-executivo-costa-mocambiqu"
}