{
    "nome": "Executivo Pântano Do Sul",
    "codigo": "4125",
    "detalhe": "Via Gramal",
    "servicos": {
        "62": [
            {
                "sentido": "Saída Pântano Do Sul",
                "horarios": [
                    {
                        "hora": "05:50",
                        "obs": [
                            {
                                "tipo": "MEIA_VIAGEM",
                                "valor": "Meia viagem"
                            }
                        ]
                    },
                    {
                        "hora": "06:15",
                        "obs": [
                            {
                                "tipo": "MEIA_VIAGEM",
                                "valor": "Meia viagem"
                            }
                        ]
                    },
                    {
                        "hora": "06:35",
                        "obs": [
                            {
                                "tipo": "MEIA_VIAGEM",
                                "valor": "Meia viagem"
                            }
                        ]
                    },
                    {
                        "hora": "07:00",
                        "obs": [
                            {
                                "tipo": "MEIA_VIAGEM",
                                "valor": "Meia viagem"
                            }
                        ]
                    },
                    {
                        "hora": "07:20",
                        "obs": [
                            {
                                "tipo": "MEIA_VIAGEM",
                                "valor": "Meia viagem"
                            }
                        ]
                    },
                    {
                        "hora": "07:40",
                        "obs": [
                            {
                                "tipo": "MEIA_VIAGEM",
                                "valor": "Meia viagem"
                            }
                        ]
                    },
                    {
                        "hora": "08:21",
                        "obs": [
                            {
                                "tipo": "PREVISTO",
                                "valor": "Horário previsto"
                            }
                        ]
                    },
                    {
                        "hora": "08:46",
                        "obs": [
                            {
                                "tipo": "PREVISTO",
                                "valor": "Horário previsto"
                            }
                        ]
                    },
                    {
                        "hora": "10:05",
                        "obs": [
                            {
                                "tipo": "PREVISTO",
                                "valor": "Horário previsto"
                            }
                        ]
                    },
                    {
                        "hora": "11:25",
                        "obs": [
                            {
                                "tipo": "PREVISTO",
                                "valor": "Horário previsto"
                            }
                        ]
                    },
                    {
                        "hora": "12:25",
                        "obs": [
                            {
                                "tipo": "PREVISTO",
                                "valor": "Horário previsto"
                            }
                        ]
                    },
                    {
                        "hora": "13:05",
                        "obs": [
                            {
                                "tipo": "PREVISTO",
                                "valor": "Horário previsto"
                            }
                        ]
                    },
                    {
                        "hora": "13:35",
                        "obs": [
                            {
                                "tipo": "PREVISTO",
                                "valor": "Horário previsto"
                            }
                        ]
                    },
                    {
                        "hora": "14:10",
                        "obs": [
                            {
                                "tipo": "PREVISTO",
                                "valor": "Horário previsto"
                            }
                        ]
                    },
                    {
                        "hora": "14:36",
                        "obs": [
                            {
                                "tipo": "PREVISTO",
                                "valor": "Horário previsto"
                            }
                        ]
                    },
                    {
                        "hora": "15:26",
                        "obs": [
                            {
                                "tipo": "PREVISTO",
                                "valor": "Horário previsto"
                            }
                        ]
                    },
                    {
                        "hora": "16:07",
                        "obs": [
                            {
                                "tipo": "PREVISTO",
                                "valor": "Horário previsto"
                            }
                        ]
                    },
                    {
                        "hora": "16:42",
                        "obs": [
                            {
                                "tipo": "PREVISTO",
                                "valor": "Horário previsto"
                            }
                        ]
                    },
                    {
                        "hora": "17:22",
                        "obs": [
                            {
                                "tipo": "PREVISTO",
                                "valor": "Horário previsto"
                            }
                        ]
                    },
                    {
                        "hora": "18:05",
                        "obs": [
                            {
                                "tipo": "PREVISTO",
                                "valor": "Horário previsto"
                            }
                        ]
                    }
                ]
            },
            {
                "sentido": "Saída Tecif - Plataforma 4 - Box 6",
                "horarios": [
                    {
                        "hora": "07:20",
                        "obs": []
                    },
                    {
                        "hora": "07:45",
                        "obs": []
                    },
                    {
                        "hora": "09:00",
                        "obs": []
                    },
                    {
                        "hora": "10:20",
                        "obs": []
                    },
                    {
                        "hora": "11:20",
                        "obs": []
                    },
                    {
                        "hora": "12:00",
                        "obs": []
                    },
                    {
                        "hora": "12:30",
                        "obs": []
                    },
                    {
                        "hora": "13:00",
                        "obs": []
                    },
                    {
                        "hora": "13:30",
                        "obs": []
                    },
                    {
                        "hora": "14:20",
                        "obs": []
                    },
                    {
                        "hora": "15:00",
                        "obs": []
                    },
                    {
                        "hora": "15:35",
                        "obs": []
                    },
                    {
                        "hora": "16:15",
                        "obs": []
                    },
                    {
                        "hora": "16:50",
                        "obs": []
                    },
                    {
                        "hora": "17:25",
                        "obs": []
                    },
                    {
                        "hora": "17:52",
                        "obs": []
                    },
                    {
                        "hora": "18:15",
                        "obs": []
                    },
                    {
                        "hora": "18:45",
                        "obs": []
                    },
                    {
                        "hora": "19:25",
                        "obs": []
                    },
                    {
                        "hora": "19:50",
                        "obs": []
                    }
                ]
            }
        ]
    },
    "tipo": "executivo",
    "slug": "4125-executivo-pantano-sul-gra"
}