{
    "nome": "Itaum / Sul",
    "codigo": "0111",
    "detalhe": "Via João Ramalho",
    "servicos": {
        "62": [
            {
                "sentido": "Ida",
                "horarios": [
                    {
                        "hora": "06:07",
                        "obs": []
                    },
                    {
                        "hora": "07:08",
                        "obs": []
                    },
                    {
                        "hora": "11:12",
                        "obs": []
                    },
                    {
                        "hora": "12:27",
                        "obs": []
                    },
                    {
                        "hora": "17:05",
                        "obs": []
                    }
                ]
            },
            {
                "sentido": "Volta",
                "horarios": [
                    {
                        "hora": "06:26",
                        "obs": []
                    },
                    {
                        "hora": "07:30",
                        "obs": []
                    },
                    {
                        "hora": "11:32",
                        "obs": []
                    },
                    {
                        "hora": "12:45",
                        "obs": []
                    },
                    {
                        "hora": "17:38",
                        "obs": []
                    }
                ]
            }
        ]
    },
    "tipo": "convencional",
    "slug": "0111-itaum-sul-joao-ramalho"
}