{
    "nome": "Iririú/Sul",
    "codigo": "6003",
    "detalhe": null,
    "servicos": {
        "62": [
            {
                "sentido": "Ida",
                "horarios": [
                    {
                        "hora": "16:57",
                        "obs": []
                    },
                    {
                        "hora": "17:10",
                        "obs": []
                    },
                    {
                        "hora": "17:30",
                        "obs": []
                    },
                    {
                        "hora": "17:45",
                        "obs": []
                    }
                ]
            },
            {
                "sentido": "Volta",
                "horarios": [
                    {
                        "hora": "17:35",
                        "obs": []
                    },
                    {
                        "hora": "17:50",
                        "obs": []
                    },
                    {
                        "hora": "18:10",
                        "obs": []
                    },
                    {
                        "hora": "18:25",
                        "obs": []
                    }
                ]
            }
        ]
    },
    "tipo": "convencional",
    "slug": "6003-iririu-sul"
}