{
    "nome": "Aririu / Florianópolis",
    "codigo": "0355",
    "detalhe": "VIA PONTE DO IMARUIM/IVO SILVEIRA",
    "servicos": {
        "62": [
            {
                "sentido": "Ida",
                "horarios": [
                    {
                        "hora": "05:15",
                        "obs": []
                    },
                    {
                        "hora": "05:50",
                        "obs": []
                    },
                    {
                        "hora": "06:10",
                        "obs": []
                    },
                    {
                        "hora": "06:20",
                        "obs": []
                    },
                    {
                        "hora": "06:35",
                        "obs": []
                    },
                    {
                        "hora": "06:50",
                        "obs": []
                    },
                    {
                        "hora": "07:10",
                        "obs": []
                    },
                    {
                        "hora": "08:00",
                        "obs": []
                    },
                    {
                        "hora": "08:30",
                        "obs": []
                    },
                    {
                        "hora": "08:45",
                        "obs": []
                    },
                    {
                        "hora": "10:40",
                        "obs": []
                    },
                    {
                        "hora": "11:00",
                        "obs": []
                    },
                    {
                        "hora": "12:00",
                        "obs": []
                    },
                    {
                        "hora": "12:15",
                        "obs": []
                    },
                    {
                        "hora": "12:40",
                        "obs": []
                    },
                    {
                        "hora": "13:30",
                        "obs": []
                    },
                    {
                        "hora": "13:55",
                        "obs": []
                    },
                    {
                        "hora": "14:20",
                        "obs": []
                    },
                    {
                        "hora": "14:40",
                        "obs": []
                    },
                    {
                        "hora": "15:00",
                        "obs": []
                    },
                    {
                        "hora": "16:10",
                        "obs": []
                    },
                    {
                        "hora": "17:00",
                        "obs": []
                    },
                    {
                        "hora": "17:20",
                        "obs": []
                    },
                    {
                        "hora": "17:50",
                        "obs": []
                    },
                    {
                        "hora": "18:20",
                        "obs": []
                    },
                    {
                        "hora": "19:10",
                        "obs": []
                    },
                    {
                        "hora": "19:40",
                        "obs": []
                    },
                    {
                        "hora": "20:15",
                        "obs": []
                    },
                    {
                        "hora": "21:15",
                        "obs": []
                    }
                ]
            },
            {
                "sentido": "Volta",
                "horarios": [
                    {
                        "hora": "06:05",
                        "obs": []
                    },
                    {
                        "hora": "07:30",
                        "obs": []
                    },
                    {
                        "hora": "09:40",
                        "obs": []
                    },
                    {
                        "hora": "10:45",
                        "obs": []
                    },
                    {
                        "hora": "11:35",
                        "obs": []
                    },
                    {
                        "hora": "12:20",
                        "obs": []
                    },
                    {
                        "hora": "12:40",
                        "obs": []
                    },
                    {
                        "hora": "13:40",
                        "obs": []
                    },
                    {
                        "hora": "14:55",
                        "obs": []
                    },
                    {
                        "hora": "15:50",
                        "obs": []
                    },
                    {
                        "hora": "16:10",
                        "obs": []
                    },
                    {
                        "hora": "16:35",
                        "obs": []
                    },
                    {
                        "hora": "16:50",
                        "obs": []
                    },
                    {
                        "hora": "17:45",
                        "obs": []
                    },
                    {
                        "hora": "18:20",
                        "obs": []
                    },
                    {
                        "hora": "19:05",
                        "obs": []
                    },
                    {
                        "hora": "21:20",
                        "obs": []
                    }
                ]
            }
        ],
        "1": [
            {
                "sentido": "Ida",
                "horarios": [
                    {
                        "hora": "05:25",
                        "obs": []
                    },
                    {
                        "hora": "06:00",
                        "obs": []
                    },
                    {
                        "hora": "06:20",
                        "obs": []
                    },
                    {
                        "hora": "06:45",
                        "obs": []
                    },
                    {
                        "hora": "07:00",
                        "obs": []
                    },
                    {
                        "hora": "07:20",
                        "obs": []
                    },
                    {
                        "hora": "07:53",
                        "obs": []
                    },
                    {
                        "hora": "08:10",
                        "obs": []
                    },
                    {
                        "hora": "08:20",
                        "obs": []
                    },
                    {
                        "hora": "08:45",
                        "obs": []
                    },
                    {
                        "hora": "09:00",
                        "obs": []
                    },
                    {
                        "hora": "09:20",
                        "obs": []
                    },
                    {
                        "hora": "09:45",
                        "obs": []
                    },
                    {
                        "hora": "10:00",
                        "obs": []
                    },
                    {
                        "hora": "10:20",
                        "obs": []
                    },
                    {
                        "hora": "10:45",
                        "obs": []
                    },
                    {
                        "hora": "11:20",
                        "obs": []
                    },
                    {
                        "hora": "11:50",
                        "obs": []
                    },
                    {
                        "hora": "12:20",
                        "obs": []
                    },
                    {
                        "hora": "13:00",
                        "obs": []
                    },
                    {
                        "hora": "14:00",
                        "obs": []
                    },
                    {
                        "hora": "16:00",
                        "obs": []
                    },
                    {
                        "hora": "17:00",
                        "obs": []
                    },
                    {
                        "hora": "18:00",
                        "obs": []
                    },
                    {
                        "hora": "19:00",
                        "obs": []
                    },
                    {
                        "hora": "20:00",
                        "obs": []
                    }
                ]
            },
            {
                "sentido": "Volta",
                "horarios": [
                    {
                        "hora": "05:40",
                        "obs": []
                    },
                    {
                        "hora": "06:30",
                        "obs": []
                    },
                    {
                        "hora": "07:00",
                        "obs": []
                    },
                    {
                        "hora": "07:20",
                        "obs": []
                    },
                    {
                        "hora": "07:50",
                        "obs": []
                    },
                    {
                        "hora": "08:20",
                        "obs": []
                    },
                    {
                        "hora": "08:55",
                        "obs": []
                    },
                    {
                        "hora": "09:20",
                        "obs": []
                    },
                    {
                        "hora": "09:50",
                        "obs": []
                    },
                    {
                        "hora": "10:50",
                        "obs": []
                    },
                    {
                        "hora": "11:20",
                        "obs": []
                    },
                    {
                        "hora": "11:50",
                        "obs": []
                    },
                    {
                        "hora": "12:20",
                        "obs": []
                    },
                    {
                        "hora": "12:50",
                        "obs": []
                    },
                    {
                        "hora": "19:15",
                        "obs": []
                    }
                ]
            }
        ],
        "64": [
            {
                "sentido": "Ida",
                "horarios": [
                    {
                        "hora": "06:30",
                        "obs": []
                    },
                    {
                        "hora": "10:30",
                        "obs": []
                    },
                    {
                        "hora": "12:30",
                        "obs": []
                    },
                    {
                        "hora": "14:30",
                        "obs": []
                    },
                    {
                        "hora": "16:30",
                        "obs": []
                    },
                    {
                        "hora": "17:00",
                        "obs": []
                    },
                    {
                        "hora": "17:20",
                        "obs": []
                    },
                    {
                        "hora": "18:30",
                        "obs": []
                    },
                    {
                        "hora": "20:00",
                        "obs": []
                    },
                    {
                        "hora": "21:00",
                        "obs": []
                    },
                    {
                        "hora": "22:00",
                        "obs": []
                    }
                ]
            },
            {
                "sentido": "Volta",
                "horarios": [
                    {
                        "hora": "06:25",
                        "obs": []
                    },
                    {
                        "hora": "07:30",
                        "obs": []
                    },
                    {
                        "hora": "09:30",
                        "obs": []
                    },
                    {
                        "hora": "11:30",
                        "obs": []
                    },
                    {
                        "hora": "13:30",
                        "obs": []
                    },
                    {
                        "hora": "15:30",
                        "obs": []
                    },
                    {
                        "hora": "17:30",
                        "obs": []
                    },
                    {
                        "hora": "18:30",
                        "obs": []
                    },
                    {
                        "hora": "20:40",
                        "obs": []
                    },
                    {
                        "hora": "21:50",
                        "obs": []
                    }
                ]
            }
        ]
    },
    "tipo": "convencional",
    "slug": "0355-aririu-fpolis"
}